[{"time": "2026-02-18 21:17:22", "callsign": "M7LXH", "tg_slot": " TG 91, 8.0 seconds, 0% packet loss, BER: 0.0%"}, {"time": "2026-02-18 21:17:39", "callsign": "9K2IC", "tg_slot": " TG 91, 15.2 seconds, 0% packet loss, BER: 0.2%"}, {"time": "2026-02-18 21:17:46", "callsign": "WX9USA", "tg_slot": " TG 91, 5.4 seconds, 0% packet loss, BER: 0.0%"}, {"time": "2026-02-18 21:18:15", "callsign": "9K2IC", "tg_slot": " TG 91, 23.2 seconds, 0% packet loss, BER: 0.2%"}, {"time": "2026-02-18 21:18:38", "callsign": "WX9USA", "tg_slot": " TG 91, 20.4 seconds, 0% packet loss, BER: 0.0%"}, {"time": "2026-02-18 21:19:10", "callsign": "9K2IC", "tg_slot": " TG 91, 29.6 seconds, 0% packet loss, BER: 0.1%"}, {"time": "2026-02-18 21:19:30", "callsign": "KF4UFO", "tg_slot": " TG 91, 13.8 seconds, 0% packet loss, BER: 0.0%"}, {"time": "2026-02-18 21:19:35", "callsign": "KF0TDV", "tg_slot": " TG 91, 2.6 seconds, 0% packet loss, BER: 0.0%"}, {"time": "2026-02-18 21:20:00", "callsign": "9K2IC", "tg_slot": " TG 91, 22.8 seconds, 0% packet loss, BER: 0.2%"}, {"time": "2026-02-18 21:20:25", "callsign": "KF4UFO", "tg_slot": " TG 91, 22.4 seconds, 0% packet loss, BER: 0.0%"}, {"time": "2026-02-18 21:21:01", "callsign": "9K2IC", "tg_slot": " TG 91, 32.5 seconds, 0% packet loss, BER: 0.2%"}, {"time": "2026-02-18 21:21:17", "callsign": "KF4UFO", "tg_slot": " TG 91, 12.4 seconds, 0% packet loss, BER: 0.0%"}, {"time": "2026-02-18 21:21:29", "callsign": "9K2IC", "tg_slot": " TG 91, 9.8 seconds, 0% packet loss, BER: 0.1%"}, {"time": "2026-02-18 21:21:41", "callsign": "M6KCI", "tg_slot": " TG 91, 9.0 seconds, 0% packet loss, BER: 0.0%"}, {"time": "2026-02-18 21:21:54", "callsign": "KF4UFO", "tg_slot": " TG 91, 8.4 seconds, 0% packet loss, BER: 0.0%"}, {"time": "2026-02-18 21:22:40", "callsign": "M6KCI", "tg_slot": " TG 91, 42.4 seconds, 0% packet loss, BER: 0.0%"}, {"time": "2026-02-18 21:22:43", "callsign": "TA3VSE", "tg_slot": " TG 91, 1.0 seconds, 0% packet loss, BER: 0.0%"}]