[{"time": "2026-02-21 10:28:18", "callsign": "EA8DFX", "tg_slot": " TG 91, 8.8 seconds, 0% packet loss, BER: 0.0%"}, {"time": "2026-02-21 10:28:25", "callsign": "TA2UIL", "tg_slot": " TG 91, 5.5 seconds, 0% packet loss, BER: 0.0%"}, {"time": "2026-02-21 10:28:39", "callsign": "TA2DGB", "tg_slot": " TG 91, 9.1 seconds, 0% packet loss, BER: 0.0%"}, {"time": "2026-02-21 10:28:58", "callsign": "YC0BPV", "tg_slot": " TG 91, 16.3 seconds, 0% packet loss, BER: 0.0%"}, {"time": "2026-02-21 10:29:16", "callsign": "EA8DFX", "tg_slot": " TG 91, 11.6 seconds, 0% packet loss, BER: 0.0%"}, {"time": "2026-02-21 10:29:35", "callsign": "TA2UIL", "tg_slot": " TG 91, 14.9 seconds, 0% packet loss, BER: 0.0%"}, {"time": "2026-02-21 10:29:43", "callsign": "VU2EHB", "tg_slot": "Iceberg, North Atlan"}, {"time": "2026-02-21 10:29:47", "callsign": "VU2EHB", "tg_slot": " TG 91, 9.5 seconds, 0% packet loss, BER: 0.0%"}, {"time": "2026-02-21 10:30:07", "callsign": "TA2UIL", "tg_slot": " TG 91, 14.9 seconds, 0% packet loss, BER: 0.0%"}, {"time": "2026-02-21 10:30:25", "callsign": "EA8DFX", "tg_slot": " TG 91, 7.3 seconds, 0% packet loss, BER: 0.0%"}, {"time": "2026-02-21 10:30:39", "callsign": "TA2UIL", "tg_slot": " TG 91, 5.9 seconds, 0% packet loss, BER: 0.0%"}, {"time": "2026-02-21 10:31:28", "callsign": "EA8DFX", "tg_slot": " TG 91, 45.1 seconds, 0% packet loss, BER: 0.0%"}, {"time": "2026-02-21 10:32:13", "callsign": "TA2UIL", "tg_slot": " TG 91, 40.8 seconds, 0% packet loss, BER: 0.0%"}, {"time": "2026-02-21 10:33:08", "callsign": "EA8DFX", "tg_slot": " TG 91, 51.2 seconds, 0% packet loss, BER: 0.0%"}, {"time": "2026-02-21 10:33:12", "callsign": "EI3GUB", "tg_slot": " TG 91, 1.6 seconds, 0% packet loss, BER: 0.0%"}, {"time": "2026-02-21 10:33:19", "callsign": "VU2EHB", "tg_slot": "Iceberg, North Atlan"}, {"time": "2026-02-21 10:33:22", "callsign": "VU2EHB", "tg_slot": " TG 91, 7.7 seconds, 0% packet loss, BER: 0.0%"}, {"time": "2026-02-21 10:33:42", "callsign": "VU2EHB", "tg_slot": "Iceberg, North Atlan"}, {"time": "2026-02-21 10:33:51", "callsign": "VU2EHB", "tg_slot": " TG 91, 14.2 seconds, 0% packet loss, BER: 0.0%"}]